setup.py
ak_s_distributions/Binomialdistribution.py
ak_s_distributions/Gaussiandistribution.py
ak_s_distributions/Generaldistribution.py
ak_s_distributions/__init__.py
ak_s_distributions.egg-info/PKG-INFO
ak_s_distributions.egg-info/SOURCES.txt
ak_s_distributions.egg-info/dependency_links.txt
ak_s_distributions.egg-info/not-zip-safe
ak_s_distributions.egg-info/top_level.txt