Metadata-Version: 1.0
Name: ak-s-distributions
Version: 0.1
Summary: Gaussian distributions
Home-page: UNKNOWN
Author: Mohd Ayan Khan
Author-email: ayan.k470777@gmail.com
License: UNKNOWN
Platform: UNKNOWN
